{
  "name": "Bernice Guerrero",
  "age": 36,
  "address": {
    "street": "Supbum Highway",
    "city": "Ajojihir",
    "state": "UT",
    "zip": "29977"
  },
  "contact": {
    "phone": "(440) 986-6940",
    "servicePhone": "800769914"
  },
  "birthday": "1964-04-29T14:04:39.927Z",
  "ip": "235.238.136.200",
  "foo": "bar",
  "profile": {
    "about": "Cuc gujov gozisfe nilag ebgi udfam demalvu gaipela owiad fisus situnom gano we zoznus citje cev jozop utu. Dulkuzveg kidec cubgo cefis bevi pihausu ugafi ut debbu kaenufif kew fel gokajgow doszewafo sij pa bi. Javwopka odofe vofugi itsik na uwtuvov rosfasele isaece cabouwu luske jacuv gujisug je pevmorit nu jevsoosu. Haadfud cam ewuwe zeito kug hi eznadlew taopodab fawpomu hinkanaj legbila akine wa ifale mu uhiuda fam. Ibe for ihi fu itpol ti lumeci rovnepzis su cuplo livjumze bi osebo raohi poub. Fad caj vulaan sajumki eslihe aje biklibvo jih sukwu ahadool utiteabo vedas pipir hot gukgichiw. Foudu mu oza nodaaf jubzu uwgiivo rasnikew arfejbev bon wemiwab dim dib kein de una vi givago.",
    "bio": "Zegita pasic gapsirozi ketpuaca ivuwef dak cohwiludu fevaj ries fid merul kacisun. Gas ik jovij vumgopu zuz owlaju il ru ni juligto foki taf wek fa jilceka oc. Jefuji ihjun jegbe kima tu sualo gaj nefnuh ejonocuw was riehoj ahof limogo udaheape zusossal enarijkec. Fucaz led nelene karzew tez paet hog me icugure veulwol te vidruzo deb tozgir ulgikug ra jilci siwimih. Pu rucedal nuhow rupwen faki zu caguku zadikis fuz lifo ja sa pumem zusah zezic mowanneh safwu. Su odgatro lu vefipwo jowi hawerfo covupku ze ikhir dewza volen vepjoz bap duvmimwa buc. Cecuhe foud um unadof ninkiblo jijo etnihaz pe sanagogow cevu lafuc hibwanjok guicohuc he."
  },
  "apiKey": "10cb8d0da7ecc0d910eff57535ce0fec1aa47f37f08d338e391110ac973d44ba",
  "currency": {
    "code": "CLP",
    "name": "Chile Peso"
  }
}